feast/__init__.py
feast/base_feature_view.py
feast/cli.py
feast/constants.py
feast/data_format.py
feast/data_source.py
feast/driver_test_data.py
feast/entity.py
feast/errors.py
feast/feast_object.py
feast/feature.py
feast/feature_server.py
feast/feature_service.py
feast/feature_store.py
feast/feature_view.py
feast/feature_view_projection.py
feast/flags.py
feast/flags_helper.py
feast/go_server.py
feast/importer.py
feast/inference.py
feast/names.py
feast/on_demand_feature_view.py
feast/online_response.py
feast/proto_json.py
feast/registry.py
feast/registry_store.py
feast/repo_config.py
feast/repo_contents.py
feast/repo_operations.py
feast/request_feature_view.py
feast/saved_dataset.py
feast/transformation_server.py
feast/type_map.py
feast/usage.py
feast/utils.py
feast/value_type.py
feast/version.py
feast/wait.py
feast/diff/__init__.py
feast/diff/infra_diff.py
feast/diff/property_diff.py
feast/diff/registry_diff.py
feast/dqm/__init__.py
feast/dqm/errors.py
feast/dqm/profilers/__init__.py
feast/dqm/profilers/ge_profiler.py
feast/dqm/profilers/profiler.py
feast/infra/__init__.py
feast/infra/aws.py
feast/infra/gcp.py
feast/infra/infra_object.py
feast/infra/key_encoding_utils.py
feast/infra/local.py
feast/infra/passthrough_provider.py
feast/infra/provider.py
feast/infra/feature_servers/aws_lambda/Dockerfile
feast/infra/feature_servers/aws_lambda/__init__.py
feast/infra/feature_servers/aws_lambda/app.py
feast/infra/feature_servers/aws_lambda/config.py
feast/infra/feature_servers/aws_lambda/requirements.txt
feast/infra/feature_servers/gcp_cloudrun/Dockerfile
feast/infra/feature_servers/gcp_cloudrun/__init__.py
feast/infra/feature_servers/gcp_cloudrun/app.py
feast/infra/feature_servers/gcp_cloudrun/config.py
feast/infra/feature_servers/gcp_cloudrun/requirements.txt
feast/infra/offline_stores/__init__.py
feast/infra/offline_stores/bigquery.py
feast/infra/offline_stores/bigquery_source.py
feast/infra/offline_stores/file.py
feast/infra/offline_stores/file_source.py
mk_feature_store-0.19.0.dist-info/METADATA
mk_feature_store-0.19.0.dist-info/WHEEL
mk_feature_store-0.19.0.dist-info/entry_points.txt
mk_feature_store-0.19.0.dist-info/top_level.txt
mk_feature_store-0.19.0.dist-info/RECORD
