Metadata-Version: 2.1
Name: mk-feature-store
Version: 0.19.0
Summary: Python SDK for Feast
Home-page: https://github.com/jungyuneum/feature-store/feast-postgres/feast
Author: Feast
License: Apache
Platform: UNKNOWN
Classifier: License :: OSI Approved :: Apache Software License
Classifier: Programming Language :: Python
Classifier: Programming Language :: Python :: 3
Classifier: Programming Language :: Python :: 3.7
Requires-Python: >=3.7.0
Requires-Dist: Click (>=7.*)
Requires-Dist: colorama (>=0.3.9)
Requires-Dist: dill (==0.3.*)
Requires-Dist: fastavro (>=1.1.0)
Requires-Dist: google-api-core (>=1.23.0)
Requires-Dist: googleapis-common-protos (==1.52.*)
Requires-Dist: grpcio (>=1.34.0)
Requires-Dist: grpcio-reflection (>=1.34.0)
Requires-Dist: Jinja2 (>=2.0.0)
Requires-Dist: jsonschema
Requires-Dist: mmh3
Requires-Dist: pandas (>=1.0.0)
Requires-Dist: pandavro (==1.5.*)
Requires-Dist: protobuf (>=3.10)
Requires-Dist: proto-plus (<1.19.7)
Requires-Dist: pyarrow (>=4.0.0)
Requires-Dist: pydantic (>=1.0.0)
Requires-Dist: PyYAML (>=5.4.*)
Requires-Dist: tabulate (==0.8.*)
Requires-Dist: tenacity (>=7.*)
Requires-Dist: toml (==0.10.*)
Requires-Dist: tqdm (==4.*)
Requires-Dist: fastapi (>=0.68.0)
Requires-Dist: uvicorn[standard] (>=0.14.0)
Requires-Dist: tensorflow-metadata (<2.0.0,>=1.0.0)
Requires-Dist: dask (<2022.02.0,>=2021.*)
Provides-Extra: aws
Requires-Dist: boto3 (>=1.17.0) ; extra == 'aws'
Requires-Dist: docker (>=5.0.2) ; extra == 'aws'
Provides-Extra: ci
Requires-Dist: cryptography (==3.3.2) ; extra == 'ci'
Requires-Dist: flake8 ; extra == 'ci'
Requires-Dist: black (==19.10b0) ; extra == 'ci'
Requires-Dist: isort (>=5) ; extra == 'ci'
Requires-Dist: grpcio-tools (==1.34.0) ; extra == 'ci'
Requires-Dist: grpcio-testing (==1.34.0) ; extra == 'ci'
Requires-Dist: minio (==7.1.0) ; extra == 'ci'
Requires-Dist: mock (==2.0.0) ; extra == 'ci'
Requires-Dist: moto ; extra == 'ci'
Requires-Dist: mypy (==0.931) ; extra == 'ci'
Requires-Dist: mypy-protobuf (==3.1.0) ; extra == 'ci'
Requires-Dist: avro (==1.10.0) ; extra == 'ci'
Requires-Dist: gcsfs ; extra == 'ci'
Requires-Dist: urllib3 (>=1.25.4) ; extra == 'ci'
Requires-Dist: psutil (==5.9.0) ; extra == 'ci'
Requires-Dist: pytest (>=6.0.0) ; extra == 'ci'
Requires-Dist: pytest-cov ; extra == 'ci'
Requires-Dist: pytest-xdist ; extra == 'ci'
Requires-Dist: pytest-benchmark (>=3.4.1) ; extra == 'ci'
Requires-Dist: pytest-lazy-fixture (==0.6.3) ; extra == 'ci'
Requires-Dist: pytest-timeout (==1.4.2) ; extra == 'ci'
Requires-Dist: pytest-ordering (==0.6.*) ; extra == 'ci'
Requires-Dist: pytest-mock (==1.10.4) ; extra == 'ci'
Requires-Dist: Sphinx (!=4.0.0,<4.4.0) ; extra == 'ci'
Requires-Dist: sphinx-rtd-theme ; extra == 'ci'
Requires-Dist: testcontainers (==3.4.2) ; extra == 'ci'
Requires-Dist: adlfs (==0.5.9) ; extra == 'ci'
Requires-Dist: firebase-admin (==4.5.2) ; extra == 'ci'
Requires-Dist: pre-commit ; extra == 'ci'
Requires-Dist: assertpy (==1.1) ; extra == 'ci'
Requires-Dist: pip-tools ; extra == 'ci'
Requires-Dist: types-protobuf ; extra == 'ci'
Requires-Dist: types-python-dateutil ; extra == 'ci'
Requires-Dist: types-pytz ; extra == 'ci'
Requires-Dist: types-PyYAML ; extra == 'ci'
Requires-Dist: types-redis ; extra == 'ci'
Requires-Dist: types-requests ; extra == 'ci'
Requires-Dist: types-setuptools ; extra == 'ci'
Requires-Dist: types-tabulate ; extra == 'ci'
Requires-Dist: google-cloud-bigquery (>=2.28.1) ; extra == 'ci'
Requires-Dist: google-cloud-bigquery-storage (>=2.0.0) ; extra == 'ci'
Requires-Dist: google-cloud-datastore (>=2.1.*) ; extra == 'ci'
Requires-Dist: google-cloud-storage (<1.41,>=1.34.*) ; extra == 'ci'
Requires-Dist: google-cloud-core (<2.0.0,>=1.4.0) ; extra == 'ci'
Requires-Dist: redis (==3.5.3) ; extra == 'ci'
Requires-Dist: redis-py-cluster (>=2.1.3) ; extra == 'ci'
Requires-Dist: hiredis (>=2.0.0) ; extra == 'ci'
Requires-Dist: boto3 (>=1.17.0) ; extra == 'ci'
Requires-Dist: docker (>=5.0.2) ; extra == 'ci'
Requires-Dist: snowflake-connector-python[pandas] (>=2.7.3) ; extra == 'ci'
Requires-Dist: pyspark (>=3.0.0) ; extra == 'ci'
Requires-Dist: great-expectations (<0.15.0,>=0.14.0) ; extra == 'ci'
Provides-Extra: dev
Requires-Dist: mypy-protobuf (>=3.1.0) ; extra == 'dev'
Requires-Dist: grpcio-testing (==1.*) ; extra == 'dev'
Requires-Dist: cryptography (==3.3.2) ; extra == 'dev'
Requires-Dist: flake8 ; extra == 'dev'
Requires-Dist: black (==19.10b0) ; extra == 'dev'
Requires-Dist: isort (>=5) ; extra == 'dev'
Requires-Dist: grpcio-tools (==1.34.0) ; extra == 'dev'
Requires-Dist: grpcio-testing (==1.34.0) ; extra == 'dev'
Requires-Dist: minio (==7.1.0) ; extra == 'dev'
Requires-Dist: mock (==2.0.0) ; extra == 'dev'
Requires-Dist: moto ; extra == 'dev'
Requires-Dist: mypy (==0.931) ; extra == 'dev'
Requires-Dist: mypy-protobuf (==3.1.0) ; extra == 'dev'
Requires-Dist: avro (==1.10.0) ; extra == 'dev'
Requires-Dist: gcsfs ; extra == 'dev'
Requires-Dist: urllib3 (>=1.25.4) ; extra == 'dev'
Requires-Dist: psutil (==5.9.0) ; extra == 'dev'
Requires-Dist: pytest (>=6.0.0) ; extra == 'dev'
Requires-Dist: pytest-cov ; extra == 'dev'
Requires-Dist: pytest-xdist ; extra == 'dev'
Requires-Dist: pytest-benchmark (>=3.4.1) ; extra == 'dev'
Requires-Dist: pytest-lazy-fixture (==0.6.3) ; extra == 'dev'
Requires-Dist: pytest-timeout (==1.4.2) ; extra == 'dev'
Requires-Dist: pytest-ordering (==0.6.*) ; extra == 'dev'
Requires-Dist: pytest-mock (==1.10.4) ; extra == 'dev'
Requires-Dist: Sphinx (!=4.0.0,<4.4.0) ; extra == 'dev'
Requires-Dist: sphinx-rtd-theme ; extra == 'dev'
Requires-Dist: testcontainers (==3.4.2) ; extra == 'dev'
Requires-Dist: adlfs (==0.5.9) ; extra == 'dev'
Requires-Dist: firebase-admin (==4.5.2) ; extra == 'dev'
Requires-Dist: pre-commit ; extra == 'dev'
Requires-Dist: assertpy (==1.1) ; extra == 'dev'
Requires-Dist: pip-tools ; extra == 'dev'
Requires-Dist: types-protobuf ; extra == 'dev'
Requires-Dist: types-python-dateutil ; extra == 'dev'
Requires-Dist: types-pytz ; extra == 'dev'
Requires-Dist: types-PyYAML ; extra == 'dev'
Requires-Dist: types-redis ; extra == 'dev'
Requires-Dist: types-requests ; extra == 'dev'
Requires-Dist: types-setuptools ; extra == 'dev'
Requires-Dist: types-tabulate ; extra == 'dev'
Requires-Dist: google-cloud-bigquery (>=2.28.1) ; extra == 'dev'
Requires-Dist: google-cloud-bigquery-storage (>=2.0.0) ; extra == 'dev'
Requires-Dist: google-cloud-datastore (>=2.1.*) ; extra == 'dev'
Requires-Dist: google-cloud-storage (<1.41,>=1.34.*) ; extra == 'dev'
Requires-Dist: google-cloud-core (<2.0.0,>=1.4.0) ; extra == 'dev'
Requires-Dist: redis (==3.5.3) ; extra == 'dev'
Requires-Dist: redis-py-cluster (>=2.1.3) ; extra == 'dev'
Requires-Dist: hiredis (>=2.0.0) ; extra == 'dev'
Requires-Dist: boto3 (>=1.17.0) ; extra == 'dev'
Requires-Dist: docker (>=5.0.2) ; extra == 'dev'
Requires-Dist: snowflake-connector-python[pandas] (>=2.7.3) ; extra == 'dev'
Requires-Dist: pyspark (>=3.0.0) ; extra == 'dev'
Requires-Dist: great-expectations (<0.15.0,>=0.14.0) ; extra == 'dev'
Provides-Extra: gcp
Requires-Dist: google-cloud-bigquery (>=2.28.1) ; extra == 'gcp'
Requires-Dist: google-cloud-bigquery-storage (>=2.0.0) ; extra == 'gcp'
Requires-Dist: google-cloud-datastore (>=2.1.*) ; extra == 'gcp'
Requires-Dist: google-cloud-storage (<1.41,>=1.34.*) ; extra == 'gcp'
Requires-Dist: google-cloud-core (<2.0.0,>=1.4.0) ; extra == 'gcp'
Provides-Extra: ge
Requires-Dist: great-expectations (<0.15.0,>=0.14.0) ; extra == 'ge'
Provides-Extra: redis
Requires-Dist: redis (==3.5.3) ; extra == 'redis'
Requires-Dist: redis-py-cluster (>=2.1.3) ; extra == 'redis'
Requires-Dist: hiredis (>=2.0.0) ; extra == 'redis'
Provides-Extra: snowflake
Requires-Dist: snowflake-connector-python[pandas] (>=2.7.3) ; extra == 'snowflake'
Provides-Extra: spark
Requires-Dist: pyspark (>=3.0.0) ; extra == 'spark'
